[
  {
    "file": "/home/chava/Tabs/Metallica - For Whom The Belll Tolls.gp4",
    "filename": "Metallica - For Whom The Belll Tolls.gp4",
    "title": "For Whom The Bell Tolls (S&M)",
    "artist": "Metallica",
    "bpm": 125,
    "bars": 149,
    "tracks": 7,
    "total_technique_hits": 12,
    "track_details": [
      {
        "number": 1,
        "name": "Vocals",
        "notes": 206,
        "bars": 149,
        "note_density": 1.38,
        "techniques": {
          "slide": 4
        }
      },
      {
        "number": 2,
        "name": "James Hetfield (Guitar)",
        "notes": 1185,
        "bars": 149,
        "note_density": 7.95,
        "techniques": {
          "palm_mute": 302
        }
      },
      {
        "number": 3,
        "name": "Kirk Hammett (Guitar)",
        "notes": 1424,
        "bars": 149,
        "note_density": 9.56,
        "techniques": {
          "bend": 11,
          "vibrato": 4,
          "slide": 2,
          "harmonic": 17,
          "palm_mute": 500
        }
      },
      {
        "number": 4,
        "name": "Orchestra",
        "notes": 197,
        "bars": 149,
        "note_density": 1.32,
        "techniques": {
          "slide": 10
        }
      },
      {
        "number": 5,
        "name": "Orchestra 2",
        "notes": 489,
        "bars": 149,
        "note_density": 3.28,
        "techniques": {
          "tremolo": 2,
          "palm_mute": 120
        }
      },
      {
        "number": 6,
        "name": "Jason Newsted (Bass)",
        "notes": 923,
        "bars": 149,
        "note_density": 6.19,
        "techniques": {
          "vibrato": 8,
          "slide": 16
        }
      },
      {
        "number": 7,
        "name": "Lars Ulrich (Drums)",
        "notes": 1223,
        "bars": 149,
        "note_density": 8.21,
        "techniques": {}
      }
    ],
    "difficulty": {
      "score": 7.4,
      "components": {
        "bpm": 0.361,
        "density": 0.382,
        "technique": 1.0,
        "diversity": 0.75
      }
    }
  },
  {
    "file": "/home/chava/Tabs/Metallica - Sad But True (3).gp4",
    "filename": "Metallica - Sad But True (3).gp4",
    "title": "Sad But True (Cunning Stunts)",
    "artist": "Metallica",
    "bpm": 86,
    "bars": 123,
    "tracks": 4,
    "total_technique_hits": 13,
    "track_details": [
      {
        "number": 1,
        "name": "James Hetfield",
        "notes": 1717,
        "bars": 123,
        "note_density": 13.96,
        "techniques": {
          "bend": 2,
          "vibrato": 11,
          "slide": 10,
          "hammer_on": 103,
          "palm_mute": 728
        }
      },
      {
        "number": 2,
        "name": "Kirk Hammett",
        "notes": 1432,
        "bars": 123,
        "note_density": 11.64,
        "techniques": {
          "bend": 33,
          "vibrato": 32,
          "slide": 15,
          "hammer_on": 79,
          "palm_mute": 498
        }
      },
      {
        "number": 3,
        "name": "Jason Newsted",
        "notes": 1089,
        "bars": 123,
        "note_density": 8.85,
        "techniques": {
          "vibrato": 7,
          "hammer_on": 81
        }
      },
      {
        "number": 4,
        "name": "Lars Ulrich",
        "notes": 1463,
        "bars": 123,
        "note_density": 11.89,
        "techniques": {
          "tremolo": 1
        }
      }
    ],
    "difficulty": {
      "score": 7.3,
      "components": {
        "bpm": 0.144,
        "density": 0.558,
        "technique": 1.0,
        "diversity": 0.75
      }
    }
  },
  {
    "file": "/home/chava/Tabs/Metallica - One (3).gp4",
    "filename": "Metallica - One (3).gp4",
    "title": "One",
    "artist": "",
    "bpm": 108,
    "bars": 233,
    "tracks": 11,
    "total_technique_hits": 29,
    "track_details": [
      {
        "number": 1,
        "name": "Gtr.I",
        "notes": 497,
        "bars": 233,
        "note_density": 2.13,
        "techniques": {
          "slide": 15,
          "hammer_on": 28
        }
      },
      {
        "number": 2,
        "name": "Gtr.II",
        "notes": 558,
        "bars": 233,
        "note_density": 2.39,
        "techniques": {
          "bend": 1,
          "vibrato": 2,
          "slide": 16,
          "hammer_on": 43
        }
      },
      {
        "number": 3,
        "name": "Gtr.III",
        "notes": 335,
        "bars": 233,
        "note_density": 1.44,
        "techniques": {
          "slide": 15,
          "hammer_on": 28
        }
      },
      {
        "number": 4,
        "name": "Gtr.IV",
        "notes": 1512,
        "bars": 233,
        "note_density": 6.49,
        "techniques": {
          "vibrato": 10,
          "slide": 11,
          "hammer_on": 27,
          "palm_mute": 911
        }
      },
      {
        "number": 5,
        "name": "Gtr.V",
        "notes": 951,
        "bars": 233,
        "note_density": 4.08,
        "techniques": {
          "bend": 8,
          "vibrato": 4,
          "slide": 5,
          "hammer_on": 2,
          "palm_mute": 501
        }
      },
      {
        "number": 6,
        "name": "Gtr.VI(solo)",
        "notes": 639,
        "bars": 233,
        "note_density": 2.74,
        "techniques": {
          "bend": 52,
          "vibrato": 12,
          "slide": 7,
          "hammer_on": 138,
          "harmonic": 1,
          "palm_mute": 69
        }
      },
      {
        "number": 7,
        "name": "Gtr.VII",
        "notes": 89,
        "bars": 233,
        "note_density": 0.38,
        "techniques": {
          "slide": 2,
          "palm_mute": 47
        }
      },
      {
        "number": 8,
        "name": "Vocals I",
        "notes": 261,
        "bars": 233,
        "note_density": 1.12,
        "techniques": {
          "slide": 5
        }
      },
      {
        "number": 9,
        "name": "Vocals II",
        "notes": 70,
        "bars": 233,
        "note_density": 0.3,
        "techniques": {
          "slide": 2
        }
      },
      {
        "number": 10,
        "name": "Drums",
        "notes": 2971,
        "bars": 233,
        "note_density": 12.75,
        "techniques": {}
      },
      {
        "number": 11,
        "name": "Bass",
        "notes": 1500,
        "bars": 233,
        "note_density": 6.44,
        "techniques": {
          "slide": 9,
          "hammer_on": 5
        }
      }
    ],
    "difficulty": {
      "score": 7.0,
      "components": {
        "bpm": 0.267,
        "density": 0.26,
        "technique": 1.0,
        "diversity": 0.75
      }
    }
  },
  {
    "file": "/home/chava/Tabs/Iron Maiden - Strange World.gp3",
    "filename": "Iron Maiden - Strange World.gp3",
    "title": "Strange World",
    "artist": "",
    "bpm": 65,
    "bars": 62,
    "tracks": 4,
    "total_technique_hits": 9,
    "track_details": [
      {
        "number": 1,
        "name": "Clean Guitar 1",
        "notes": 443,
        "bars": 62,
        "note_density": 7.15,
        "techniques": {
          "slide": 24,
          "harmonic": 79
        }
      },
      {
        "number": 2,
        "name": "Clean Guitar 2",
        "notes": 1008,
        "bars": 62,
        "note_density": 16.26,
        "techniques": {
          "slide": 3
        }
      },
      {
        "number": 3,
        "name": "Lead Guitar",
        "notes": 221,
        "bars": 62,
        "note_density": 3.56,
        "techniques": {
          "bend": 30,
          "vibrato": 15,
          "slide": 13,
          "hammer_on": 44,
          "harmonic": 2
        }
      },
      {
        "number": 4,
        "name": "Bass Guitar",
        "notes": 547,
        "bars": 62,
        "note_density": 8.82,
        "techniques": {
          "slide": 31
        }
      }
    ],
    "difficulty": {
      "score": 6.6,
      "components": {
        "bpm": 0.028,
        "density": 0.65,
        "technique": 0.87,
        "diversity": 0.625
      }
    }
  },
  {
    "file": "/home/chava/Tabs/Hypocrisy - Slave To The Parasites.gp5",
    "filename": "Hypocrisy - Slave To The Parasites.gp5",
    "title": "Slave To The Parasites",
    "artist": "Hypocrisy",
    "bpm": 200,
    "bars": 247,
    "tracks": 5,
    "total_technique_hits": 6,
    "track_details": [
      {
        "number": 1,
        "name": "Peter T\u00e4gtgren",
        "notes": 1280,
        "bars": 247,
        "note_density": 5.18,
        "techniques": {
          "hammer_on": 4,
          "palm_mute": 40
        }
      },
      {
        "number": 2,
        "name": "Peter Ryth.",
        "notes": 1696,
        "bars": 247,
        "note_density": 6.87,
        "techniques": {
          "hammer_on": 6,
          "palm_mute": 57
        }
      },
      {
        "number": 3,
        "name": "Basse",
        "notes": 954,
        "bars": 247,
        "note_density": 3.86,
        "techniques": {
          "hammer_on": 4,
          "palm_mute": 41
        }
      },
      {
        "number": 4,
        "name": "Synth\u00e9",
        "notes": 54,
        "bars": 247,
        "note_density": 0.22,
        "techniques": {}
      },
      {
        "number": 5,
        "name": "HorgH",
        "notes": 2200,
        "bars": 247,
        "note_density": 8.91,
        "techniques": {}
      }
    ],
    "difficulty": {
      "score": 4.9,
      "components": {
        "bpm": 0.778,
        "density": 0.275,
        "technique": 0.417,
        "diversity": 0.25
      }
    }
  },
  {
    "file": "/home/chava/Tabs/Hypocrisy - Seeds Of The Chosen One.gp4",
    "filename": "Hypocrisy - Seeds Of The Chosen One.gp4",
    "title": "Seeds of the chosen one",
    "artist": "Hypocrisy",
    "bpm": 115,
    "bars": 102,
    "tracks": 4,
    "total_technique_hits": 3,
    "track_details": [
      {
        "number": 1,
        "name": "Peter 1",
        "notes": 1202,
        "bars": 102,
        "note_density": 11.78,
        "techniques": {
          "hammer_on": 12,
          "palm_mute": 22
        }
      },
      {
        "number": 2,
        "name": "Peter 2",
        "notes": 1218,
        "bars": 102,
        "note_density": 11.94,
        "techniques": {
          "palm_mute": 64
        }
      },
      {
        "number": 3,
        "name": "Mikael",
        "notes": 922,
        "bars": 102,
        "note_density": 9.04,
        "techniques": {}
      },
      {
        "number": 4,
        "name": "Percuss\u00e3o",
        "notes": 1634,
        "bars": 102,
        "note_density": 16.02,
        "techniques": {}
      }
    ],
    "difficulty": {
      "score": 3.7,
      "components": {
        "bpm": 0.306,
        "density": 0.478,
        "technique": 0.247,
        "diversity": 0.25
      }
    }
  },
  {
    "file": "/home/chava/Tabs/Mercyful Fate - Melissa (2).gp4",
    "filename": "Mercyful Fate - Melissa (2).gp4",
    "title": "Melissa",
    "artist": "Mercyful Fate",
    "bpm": 116,
    "bars": 181,
    "tracks": 4,
    "total_technique_hits": 4,
    "track_details": [
      {
        "number": 1,
        "name": "Drums",
        "notes": 3857,
        "bars": 181,
        "note_density": 21.31,
        "techniques": {}
      },
      {
        "number": 2,
        "name": "Rythm",
        "notes": 1340,
        "bars": 181,
        "note_density": 7.4,
        "techniques": {
          "vibrato": 1
        }
      },
      {
        "number": 3,
        "name": "Lead",
        "notes": 1104,
        "bars": 181,
        "note_density": 6.1,
        "techniques": {
          "bend": 13,
          "slide": 2,
          "harmonic": 1
        }
      },
      {
        "number": 4,
        "name": "Bass",
        "notes": 709,
        "bars": 181,
        "note_density": 3.92,
        "techniques": {}
      }
    ],
    "difficulty": {
      "score": 3.5,
      "components": {
        "bpm": 0.311,
        "density": 0.296,
        "technique": 0.187,
        "diversity": 0.5
      }
    }
  }
]